{
  "players": [
    {
      "name": "Corbin",
      "teams": [
        {
          "team": "Reds",
          "pick": "Over",
          "line": 80.5,
          "wins": 31,
          "losses": 30,
          "guess": 85,
          "pace": 82.3,
          "correct": true,
          "diff": -2.7
        },
        {
          "team": "Padres",
          "pick": "Over",
          "line": 83.5,
          "wins": 32,
          "losses": 29,
          "guess": 84,
          "pace": 85.0,
          "correct": true,
          "diff": 1.0
        },
        {
          "team": "Phillies",
          "pick": "Over",
          "line": 89.5,
          "wins": 33,
          "losses": 29,
          "guess": 90,
          "pace": 86.2,
          "correct": false,
          "diff": -3.8
        },
        {
          "team": "Cardinals",
          "pick": "Under",
          "line": 69.5,
          "wins": 32,
          "losses": 28,
          "guess": 66,
          "pace": 86.4,
          "correct": false,
          "diff": 20.4
        },
        {
          "team": "Blue Jays",
          "pick": "Under",
          "line": 88.5,
          "wins": 30,
          "losses": 33,
          "guess": 87,
          "pace": 77.1,
          "correct": true,
          "diff": -9.9
        }
      ],
      "correct": 3,
      "tiebreaker": 13.5
    },
    {
      "name": "Liam",
      "teams": [
        {
          "team": "White Sox",
          "pick": "Under",
          "line": 67.5,
          "wins": 33,
          "losses": 29,
          "guess": 64,
          "pace": 86.2,
          "correct": false,
          "diff": 22.2
        },
        {
          "team": "Rangers",
          "pick": "Over",
          "line": 83.5,
          "wins": 30,
          "losses": 32,
          "guess": 87,
          "pace": 78.4,
          "correct": false,
          "diff": -8.6
        },
        {
          "team": "Orioles",
          "pick": "Under",
          "line": 85.5,
          "wins": 30,
          "losses": 33,
          "guess": 77,
          "pace": 77.1,
          "correct": true,
          "diff": 0.1
        },
        {
          "team": "Marlins",
          "pick": "Over",
          "line": 72.5,
          "wins": 29,
          "losses": 34,
          "guess": 80,
          "pace": 74.6,
          "correct": true,
          "diff": -5.4
        },
        {
          "team": "Rays",
          "pick": "Over",
          "line": 77.5,
          "wins": 36,
          "losses": 23,
          "guess": 81,
          "pace": 98.8,
          "correct": true,
          "diff": 17.8
        }
      ],
      "correct": 3,
      "tiebreaker": 23.4
    },
    {
      "name": "Will",
      "teams": [
        {
          "team": "Brewers",
          "pick": "Over",
          "line": 84.5,
          "wins": 37,
          "losses": 23,
          "guess": 88,
          "pace": 99.9,
          "correct": true,
          "diff": 11.9
        },
        {
          "team": "Pirates",
          "pick": "Over",
          "line": 78.5,
          "wins": 34,
          "losses": 29,
          "guess": 81,
          "pace": 87.4,
          "correct": true,
          "diff": 6.4
        },
        {
          "team": "Dodgers",
          "pick": "Under",
          "line": 102.5,
          "wins": 40,
          "losses": 23,
          "guess": 97,
          "pace": 102.9,
          "correct": false,
          "diff": 5.9
        },
        {
          "team": "Angels",
          "pick": "Under",
          "line": 70.5,
          "wins": 24,
          "losses": 39,
          "guess": 69,
          "pace": 61.7,
          "correct": true,
          "diff": -7.3
        },
        {
          "team": "Twins",
          "pick": "Under",
          "line": 72.5,
          "wins": 29,
          "losses": 35,
          "guess": 71,
          "pace": 73.4,
          "correct": false,
          "diff": 2.4
        }
      ],
      "correct": 3,
      "tiebreaker": 25.6
    },
    {
      "name": "Nate",
      "teams": [
        {
          "team": "Braves",
          "pick": "Over",
          "line": 86.5,
          "wins": 42,
          "losses": 21,
          "guess": 89,
          "pace": 108.0,
          "correct": true,
          "diff": 19.0
        },
        {
          "team": "D-backs",
          "pick": "Over",
          "line": 79.5,
          "wins": 33,
          "losses": 29,
          "guess": 82,
          "pace": 86.2,
          "correct": true,
          "diff": 4.2
        },
        {
          "team": "Nationals",
          "pick": "Under",
          "line": 65.5,
          "wins": 31,
          "losses": 32,
          "guess": 58,
          "pace": 79.7,
          "correct": false,
          "diff": 21.7
        },
        {
          "team": "Guardians",
          "pick": "Over",
          "line": 79.5,
          "wins": 36,
          "losses": 28,
          "guess": 81,
          "pace": 91.1,
          "correct": true,
          "diff": 10.1
        },
        {
          "team": "Rockies",
          "pick": "Under",
          "line": 54.5,
          "wins": 24,
          "losses": 39,
          "guess": 49,
          "pace": 61.7,
          "correct": false,
          "diff": 12.7
        }
      ],
      "correct": 3,
      "tiebreaker": 33.4
    },
    {
      "name": "Sam",
      "teams": [
        {
          "team": "Yankees",
          "pick": "Over",
          "line": 90.5,
          "wins": 37,
          "losses": 25,
          "guess": 95,
          "pace": 96.7,
          "correct": true,
          "diff": 1.7
        },
        {
          "team": "Mariners",
          "pick": "Over",
          "line": 89.5,
          "wins": 33,
          "losses": 30,
          "guess": 97,
          "pace": 84.9,
          "correct": false,
          "diff": -12.1
        },
        {
          "team": "Tigers",
          "pick": "Over",
          "line": 85.5,
          "wins": 25,
          "losses": 38,
          "guess": 102,
          "pace": 64.3,
          "correct": false,
          "diff": -37.7
        },
        {
          "team": "Royals",
          "pick": "Over",
          "line": 82.5,
          "wins": 25,
          "losses": 38,
          "guess": 92,
          "pace": 64.3,
          "correct": false,
          "diff": -27.7
        },
        {
          "team": "Giants",
          "pick": "Under",
          "line": 80.5,
          "wins": 25,
          "losses": 38,
          "guess": 74,
          "pace": 64.3,
          "correct": true,
          "diff": -9.7
        }
      ],
      "correct": 2,
      "tiebreaker": 11.4
    },
    {
      "name": "Mason",
      "teams": [
        {
          "team": "Cubs",
          "pick": "Over",
          "line": 88.5,
          "wins": 33,
          "losses": 30,
          "guess": 98,
          "pace": 84.9,
          "correct": false,
          "diff": -13.1
        },
        {
          "team": "Mets",
          "pick": "Under",
          "line": 90.5,
          "wins": 27,
          "losses": 35,
          "guess": 85,
          "pace": 70.5,
          "correct": true,
          "diff": -14.5
        },
        {
          "team": "Athletics",
          "pick": "Under",
          "line": 75.5,
          "wins": 30,
          "losses": 32,
          "guess": 68,
          "pace": 78.4,
          "correct": false,
          "diff": 10.4
        },
        {
          "team": "Astros",
          "pick": "Over",
          "line": 86.5,
          "wins": 28,
          "losses": 36,
          "guess": 90,
          "pace": 70.9,
          "correct": false,
          "diff": -19.1
        },
        {
          "team": "Red Sox",
          "pick": "Under",
          "line": 87.5,
          "wins": 26,
          "losses": 35,
          "guess": 86,
          "pace": 69.0,
          "correct": true,
          "diff": -17.0
        }
      ],
      "correct": 2,
      "tiebreaker": 31.4
    }
  ],
  "last_updated": "June 05, 2026, 08:28 AM"
}